postman_py/__init__.py
postman_py/main.py
postman_py-0.2.0.dist-info/AUTHORS.rst
postman_py-0.2.0.dist-info/LICENSE
postman_py-0.2.0.dist-info/METADATA
postman_py-0.2.0.dist-info/WHEEL
postman_py-0.2.0.dist-info/top_level.txt
postman_py-0.2.0.dist-info/RECORD
