Metadata-Version: 2.1
Name: postman-py
Version: 0.2.0
Summary: Postman-Py provides a thin wrappers around the built-in package for sending mail.
Home-page: https://github.com/alexmacniven/postman_py
Author: Alex Macniven
Author-email: alex_macniven@icloud.com
License: MIT license
Keywords: postman_py
Platform: UNKNOWN
Classifier: Development Status :: 2 - Pre-Alpha
Classifier: Intended Audience :: Developers
Classifier: License :: OSI Approved :: MIT License
Classifier: Natural Language :: English
Classifier: Programming Language :: Python :: 3
Classifier: Programming Language :: Python :: 3.10
Requires-Python: >=3.10
License-File: LICENSE
License-File: AUTHORS.rst
